AUTHORS.rst
HISTORY.rst
mt_metadata/__init__.py
mt_metadata/helper_functions.py
mt_metadata/base/__init__.py
mt_metadata/base/helpers.py
mt_metadata/base/metadata.py
mt_metadata/base/pydantic_helpers.py
mt_metadata/base/schema.py
mt_metadata/common/__init__.py
mt_metadata/common/band.py
mt_metadata/common/citation.py
mt_metadata/common/comment.py
mt_metadata/common/copyright.py
mt_metadata/common/data_quality.py
mt_metadata/common/declination.py
mt_metadata/common/enumerations.py
mt_metadata/common/fdsn.py
mt_metadata/common/funding_source.py
mt_metadata/common/geographic_location.py
mt_metadata/common/instrument.py
mt_metadata/common/list_dict.py
mt_metadata/common/location.py
mt_metadata/common/mttime.py
mt_metadata/common/orientation.py
mt_metadata/common/person.py
mt_metadata/common/provenance.py
mt_metadata/common/range.py
mt_metadata/common/rating.py
mt_metadata/common/software.py
mt_metadata/common/time_period.py
mt_metadata/common/units.py
mt_metadata/data/__init__.py
mt_metadata/data/licenses.json
mt_metadata/data/mt_xml/__init__.py
mt_metadata/data/mt_xml/multi_run_experiment.xml
mt_metadata/data/mt_xml/multi_run_experiment_02.xml
mt_metadata/data/mt_xml/single_station_mt_experiment.xml
mt_metadata/data/stationxml/__init__.py
mt_metadata/data/stationxml/fdsn_no_mt_info.xml
mt_metadata/data/stationxml/mtml_electrode_example.xml
mt_metadata/data/stationxml/mtml_magnetometer_example.xml
mt_metadata/data/stationxml/mtml_single_station.xml
mt_metadata/data/stationxml/multiple_networks_example.xml
mt_metadata/data/stationxml/readme
mt_metadata/data/stationxml/station_xml_with_fap_example.xml
mt_metadata/data/stationxml/station_xml_with_fir_example.xml
mt_metadata/data/transfer_functions/NMX20.xml
mt_metadata/data/transfer_functions/PHXTest01.edi
mt_metadata/data/transfer_functions/__init__.py
mt_metadata/data/transfer_functions/example.xml
mt_metadata/data/transfer_functions/example_mtedit_cfg.txt
mt_metadata/data/transfer_functions/example_mtft24_cfg.txt
mt_metadata-1.0.1.dist-info/licenses/AUTHORS.rst
mt_metadata-1.0.1.dist-info/licenses/LICENSE
mt_metadata-1.0.1.dist-info/METADATA
mt_metadata-1.0.1.dist-info/WHEEL
mt_metadata-1.0.1.dist-info/top_level.txt
mt_metadata-1.0.1.dist-info/RECORD
