Metadata-Version: 2.4
Name: mt_metadata
Version: 1.0.1
Summary: Metadata for magnetotelluric data
Author: Anna Kelbert, Karl Kappler, Lindsey Heagy, Andy Frassetto, Tim Ronan
Author-email: Jared Peacock <jpeacock@usgs.gov>
License: MIT License
Project-URL: Homepage, https://github.com/kujaku11/mt_metadata
Project-URL: Repository, https://github.com/kujaku11/mt_metadata
Project-URL: Documentation, https://mt-metadata.readthedocs.io/
Keywords: mt_metadata
Classifier: Development Status :: 5 - Production/Stable
Classifier: Intended Audience :: Science/Research
Classifier: License :: OSI Approved :: MIT License
Classifier: Natural Language :: English
Classifier: Programming Language :: Python :: 3
Classifier: Programming Language :: Python :: 3.10
Classifier: Programming Language :: Python :: 3.11
Classifier: Programming Language :: Python :: 3.12
Requires-Python: >=3.10
License-File: LICENSE
License-File: AUTHORS.rst
Requires-Dist: numpy
Requires-Dist: scipy
Requires-Dist: pandas
Requires-Dist: matplotlib
Requires-Dist: xarray
Requires-Dist: loguru
Requires-Dist: pydantic[email]>=2.0.0
Requires-Dist: pyproj>=3.4.0
Requires-Dist: typing_extensions>=4.0.0
Provides-Extra: obspy
Requires-Dist: obspy; extra == "obspy"
Provides-Extra: test
Requires-Dist: pytest>=3; extra == "test"
Requires-Dist: pytest-subtests; extra == "test"
Requires-Dist: pytest-cov; extra == "test"
Dynamic: license-file
